ubermag/__init__.py
ubermag/info.py
ubermag/tests/__init__.py
ubermag/tests/test_info.py
ubermag/tests/test_init.py
ubermag-2025.6.dist-info/licenses/LICENSE
ubermag-2025.6.dist-info/METADATA
ubermag-2025.6.dist-info/WHEEL
ubermag-2025.6.dist-info/top_level.txt
ubermag-2025.6.dist-info/RECORD
