Metadata-Version: 2.4
Name: ubermag
Version: 2025.6
Summary: Meta package for Ubermag project.
Author: Marijan Beg, Martin Lang, Samuel Holt, Swapneel Amit Pathak, Ryan A. Pepper, Thomas Kluyver, Jeroen Mulkers, Jonathan Leliaert, Hans Fangohr
License-Expression: BSD-3-Clause
Project-URL: homepage, https://ubermag.github.io
Project-URL: documentation, https://ubermag.github.io/documentation/ubermag
Project-URL: repository, https://github.com/ubermag/ubermag
Classifier: Development Status :: 5 - Production/Stable
Classifier: Intended Audience :: Education
Classifier: Intended Audience :: Developers
Classifier: Intended Audience :: Science/Research
Classifier: Natural Language :: English
Classifier: Operating System :: MacOS
Classifier: Operating System :: Microsoft :: Windows
Classifier: Operating System :: Unix
Classifier: Programming Language :: Python :: 3 :: Only
Classifier: Topic :: Scientific/Engineering :: Physics
Classifier: Topic :: Scientific/Engineering :: Mathematics
Classifier: Topic :: Scientific/Engineering :: Visualization
Requires-Python: >=3.9
License-File: LICENSE
Requires-Dist: ubermagutil==0.64.0
Requires-Dist: discretisedfield==0.92.0
Requires-Dist: ubermagtable==0.62.0
Requires-Dist: micromagneticmodel==0.65.0
Requires-Dist: micromagneticdata==0.66.0
Requires-Dist: micromagnetictests==0.64.0
Requires-Dist: mumax3c==0.4.0
Requires-Dist: oommfc==0.66.0
Requires-Dist: mag2exp==0.64.0
Requires-Dist: jupyterlab>=3.0
Provides-Extra: dev
Requires-Dist: build; extra == "dev"
Requires-Dist: invoke; extra == "dev"
Requires-Dist: nbval; extra == "dev"
Requires-Dist: pre-commit; extra == "dev"
Requires-Dist: pytest-cov; extra == "dev"
Requires-Dist: twine; extra == "dev"
Requires-Dist: tomli; python_version < "3.11" and extra == "dev"
Dynamic: license-file
